odoo/addons/operating_unit/README.rst
odoo/addons/operating_unit/__init__.py
odoo/addons/operating_unit/__manifest__.py
odoo/addons/operating_unit/data/operating_unit_data.xml
odoo/addons/operating_unit/demo/operating_unit_demo.xml
odoo/addons/operating_unit/models/__init__.py
odoo/addons/operating_unit/models/operating_unit.py
odoo/addons/operating_unit/models/res_users.py
odoo/addons/operating_unit/security/ir.model.access.csv
odoo/addons/operating_unit/security/operating_unit_security.xml
odoo/addons/operating_unit/static/description/icon.png
odoo/addons/operating_unit/view/operating_unit_view.xml
odoo/addons/operating_unit/view/res_users_view.xml
odoo11_addon_operating_unit-11.0.1.0.0.dist-info/DESCRIPTION.rst
odoo11_addon_operating_unit-11.0.1.0.0.dist-info/METADATA
odoo11_addon_operating_unit-11.0.1.0.0.dist-info/RECORD
odoo11_addon_operating_unit-11.0.1.0.0.dist-info/WHEEL
odoo11_addon_operating_unit-11.0.1.0.0.dist-info/metadata.json
odoo11_addon_operating_unit-11.0.1.0.0.dist-info/top_level.txt
